craedl/__init__.py
craedl/__main__.py
craedl/cache.py
craedl/core.py
craedl/errors.py
craedl/version.py
craedl-1.0.3.dist-info/LICENSE
craedl-1.0.3.dist-info/METADATA
craedl-1.0.3.dist-info/WHEEL
craedl-1.0.3.dist-info/entry_points.txt
craedl-1.0.3.dist-info/top_level.txt
craedl-1.0.3.dist-info/RECORD
