Metadata-Version: 2.1
Name: craedl
Version: 1.0.3
Summary: A Python SDK for Craedl
Home-page: https://github.com/craedl/craedl-sdk-python
Author: Craedl.org
Author-email: webmaster@craedl.org
License: UNKNOWN
Platform: UNKNOWN
Classifier: Programming Language :: Python :: 3
Classifier: License :: OSI Approved :: Apache Software License
Classifier: Operating System :: OS Independent
Requires-Python: >=3.7
License-File: LICENSE
Requires-Dist: python-dateutil
Requires-Dist: requests
Requires-Dist: requests-toolbelt
